{"nodes": [{"id": "training_meta_learning_ts", "label": "meta_learning.ts", "file_type": "code", "source_file": "training\\meta_learning.ts", "source_location": "L1"}], "edges": [{"source": "training_meta_learning_ts", "target": "fs", "relation": "imports_from", "confidence": "EXTRACTED", "source_file": "training\\meta_learning.ts", "source_location": "L116", "weight": 1.0}, {"source": "training_meta_learning_ts", "target": "path", "relation": "imports_from", "confidence": "EXTRACTED", "source_file": "training\\meta_learning.ts", "source_location": "L117", "weight": 1.0}]}